Metadata-Version: 1.0
Name: xkcd-probability
Version: 0.5
Summary: Gaussian & Binomial distributions
Home-page: UNKNOWN
Author: T.I. Szatmari
Author-email: test-email@gmail.com
License: UNKNOWN
Platform: UNKNOWN
